fastrpc/__init__.py
fastrpc/file_handler.py
fastrpc/todo.py
mu/__init__.py
mu/file_handler.py
mu/todo.py
page/__init__.py
page/file_handler.py
page/todo.py
pytodos/__init__.py
pytodos/file_handler.py
pytodos/todo.py
rapidrpc/__init__.py
rapidrpc/file_handler.py
rapidrpc/todo.py
vn/__init__.py
vn/file_handler.py
vn/todo.py
vn-1.0.16.dist-info/DESCRIPTION.rst
vn-1.0.16.dist-info/METADATA
vn-1.0.16.dist-info/RECORD
vn-1.0.16.dist-info/WHEEL
vn-1.0.16.dist-info/entry_points.txt
vn-1.0.16.dist-info/metadata.json
vn-1.0.16.dist-info/top_level.txt
yy/__init__.py
yy/file_handler.py
yy/todo.py
